sample_python_clamav_test/__init__.py
sample_python_clamav_test/main.py
sample_python_clamav_test/test_eicar.txt
test_eicar-0.1.0.dist-info/METADATA
test_eicar-0.1.0.dist-info/WHEEL
test_eicar-0.1.0.dist-info/top_level.txt
test_eicar-0.1.0.dist-info/RECORD
