Metadata-Version: 2.4
Name: test_eicar
Version: 0.1.0
Summary: A sample Python package with EICAR signature for AV testing
Dynamic: summary
